WRITEBACK/WRITEBACK.v
module WRITEBACK(
    input clock,
    input reset,
    input DE_regwrite,
    input [4:0] rd,
    input [31:0] EM_Result
);
 // 32 memory locations each 32 bits wide
reg [31:0] reg_omemory [10:0];
        //  When reset is triggered, we initialize the registers with some values
    always @(posedge reset)
    begin
         reg_omemory[0] = 32'h00;
         reg_omemory[1] = 32'h00;
         reg_omemory[2] = 32'h00;
         reg_omemory[3] = 32'h00;
         reg_omemory[4] = 32'h00;
		 reg_omemory[5] = 32'h00;
         reg_omemory[6] = 32'h00;
         reg_omemory[7] = 32'h00;
         reg_omemory[8] = 32'h00;
         reg_omemory[9] = 32'h00;
         reg_omemory[10] = 32'h00;
    end

    // If clock edge is positive and regwrite is 1, we write data to specified register
    always @(posedge clock)
    begin

        if (DE_regwrite) begin
            reg_omemory[rd] = EM_Result;
        end     
    end
endmodule

EXECUTE/EXECUTE.v
module EXECUTE (
    input [31:0] in1,in2, 
    input [3:0] DE_control,
    output reg [31:0] EM_Result,
    output reg EM_zero_flag
);
    always @(*)
    begin
        // Operating based on control input
        case(DE_control)

        4'b0000: EM_Result = in1&in2;
        4'b0001: EM_Result = in1|in2;
        4'b0010: EM_Result = in1+in2;
        4'b0100: EM_Result = in1-in2;
        4'b1000: begin 
            if(in1<in2)
            EM_Result = 1;
            else
            EM_Result = 0;
        end
        4'b0011: EM_Result = in1<<in2;
        4'b0101: EM_Result = in1>>in2;
        4'b0110: EM_Result = in1*in2;
        4'b0111: EM_Result = in1^in2;

        endcase

        // Setting Zero_flag if ALU_result is zero
        if (EM_Result == 0)
            EM_zero_flag = 1'b1;
        else
            EM_zero_flag = 1'b0;
        
    end
endmodule

MEMORY/REG_MEM/REG_MEM.v
module REG_MEM(
    input [4:0] read_reg_num1,
    input [4:0] read_reg_num2,
    output [31:0] read_data1,
    output [31:0] read_data2,
    input clock,
    input reset
);

    reg [31:0] reg_imemory [20:0]; // 32 memory locations each 32 bits wide

    //  When reset is triggered, we initialize the registers with some values
    always @(posedge reset)
    begin
        // Bear with me for now, I tried using loops, but it won't work
        // Just duct-taping this for now
         reg_imemory[0] = 32'h0;
         reg_imemory[1] = 32'h0;
         reg_imemory[2] = 32'h0;
         reg_imemory[3] = 32'h3;
         reg_imemory[4] = 32'h4;
         reg_imemory[5] = 32'h5;
         reg_imemory[6] = 32'h6;
         reg_imemory[7] = 32'h7;
         reg_imemory[8] = 32'h8;
         reg_imemory[9] = 32'h9;
         reg_imemory[10] = 32'h10;
         reg_imemory[12] = 32'h12;
         reg_imemory[13] = 32'h13;
         reg_imemory[14] = 32'h14;
         reg_imemory[15] = 32'h15;
         reg_imemory[17] = 32'h17;
         reg_imemory[18] = 32'h18;
         reg_imemory[19] = 32'h19;
         reg_imemory[20] = 32'h20;
         
    end

    // The register file will always output the vaules corresponding to read register numbers 
    // It is independent of any other signal
    assign read_data1 = reg_imemory[read_reg_num1];
    assign read_data2 = reg_imemory[read_reg_num2];


endmodule

DECODE/DECODE.v
`include "./../MEMORY/REG_MEM/REG_MEM.v"

module DECODE(
    input clock,
    input [31:0] FD_Inst_Code,
    output reg [3:0] DE_control,
    output [31:0] in1,
    output [31:0] in2,
    output reg [4:0] rd
);
    reg [2:0]funct3;
    reg [6:0]funct7;
    reg [6:0]opcode;
    reg [4:0]rs1;
    reg [4:0]rs2;
    reg DE_regwrite;

      // Assign values to the internal signals within an always block
    always @(posedge clock) begin
        // Decode instruction and assign values to signals
        funct3  = FD_Inst_Code[14:12];
        funct7  = FD_Inst_Code[31:25];
        opcode  = FD_Inst_Code[6:0];
        rs1     = FD_Inst_Code[19:15];
        rs2     = FD_Inst_Code[24:20];
        rd      = FD_Inst_Code[11:7];
    end


    REG_MEM reg_file_module(
    rs1,
    rs2,
    in1,
    in2,
    clock,
    reset
    );


    always @(funct3 or funct7 or opcode)
    begin
        if (opcode == 7'b0110011) begin // R-type instructions

            DE_regwrite = 1;

            case (funct3)
                0: begin
                    if(funct7 == 0)
                    DE_control = 4'b0010; // ADD
                    else if(funct7 == 32)
                    DE_control = 4'b0100; // SUB
                end
                6: DE_control = 4'b0001; // OR
                7: DE_control = 4'b0000; // AND
                1: DE_control = 4'b0011; // SLL
                5: DE_control = 4'b0101; // SRL
				2: DE_control = 4'b0110; // MUL
				4: DE_control = 4'b0111; // XOR
            endcase

      end

    end

endmodule

MEMORY/INST_MEM/INST_MEM.v
module INST_MEM(
    input [31:0] PC,
    input reset,
    input wire clock,
    output reg [7:0] MD_Memory
);
    reg [7:0] Memory [31:0]; // Byte addressable memory with 32 locations

    // Under normal operation (reset = 0), we assign the instr. code, based on PC
    always @(posedge clock) begin
        MD_Memory <= Memory[PC];
    end

    // Initializing memory when reset is one
    always @(reset)
    begin
        // Setting 32-bit instruction: add t1, s0,s1 => 0x00940333 
            Memory[3] = 8'h00;
            Memory[2] = 8'h20;
            Memory[1] = 8'h8b;
            Memory[0] = 8'h33;
            // Setting 32-bit instruction: sub t2, s2, s3 => 0x413903b3
            Memory[7] = 8'h40;
            Memory[6] = 8'h41;
            Memory[5] = 8'h8b;
            Memory[4] = 8'hb3;
            // Setting 32-bit instruction: mul t0, s4, s5 => 0x035a02b3
            Memory[11] = 8'h02;
            Memory[10] = 8'h62;
            Memory[9] = 8'h8c;
            Memory[8] = 8'h33;
            // Setting 32-bit instruction: xor t3, s6, s7 => 0x017b4e33
            Memory[15] = 8'h00;
            Memory[14] = 8'h83;
            Memory[13] = 8'hcc;
            Memory[12] = 8'hb3;
            // Setting 32-bit instruction: sll t4, s8, s9
            Memory[19] = 8'h00;
            Memory[18] = 8'ha4;
            Memory[17] = 8'h9d;
            Memory[16] = 8'h33;
            // Setting 32-bit instruction: srl t5, s10, s11
            Memory[23] = 8'h00;
            Memory[22] = 8'hc5;
            Memory[21] = 8'hdd;
            Memory[20] = 8'hb3;
            // Setting 32-bit instruction: and t6, a2, a3
            Memory[27] = 8'h00;
            Memory[26] = 8'he6;
            Memory[25] = 8'h7e;
            Memory[24] = 8'h33;
            // Setting 32-bit instruction: or a7, a4, a5
            Memory[31] = 8'h01;
            Memory[30] = 8'h07;
            Memory[29] = 8'he8;
            Memory[28] = 8'hb3;
    end

endmodule

FETCH/FETCH.v
`include "./../MEMORY/INST_MEM/INST_MEM.v"

module FETCH(
    input clock,
    input reset,
    output [31:0] FD_Inst_code
);
reg [31:0] PC = 32'b0;  // 32-bit program counter is initialized to zero
wire [7:0] MD_Memory;
    // Initializing the instruction memory block
    INST_MEM inst_mem (
        .PC(PC),
        .reset(reset),
        .clock(clock),
        .MD_Memory(MD_Memory)
    );


    assign FD_Inst_Code = {MD_Memory[PC+3],MD_Memory[PC+2],MD_Memory[PC+1],MD_Memory[PC]};

    always @(posedge clock, posedge reset)
    begin
        if(reset == 1)  //If reset is one, clear the program counter
        PC <= 0;
        else
        PC <= PC+4;   // Increment program counter on positive clock edge
    end

endmodule

PROCESSOR/PROCESSOR.v
`include "./../DECODE/DECODE.v"
`include "./../EXECUTE/EXECUTE.v"
`include "./../FETCH/FETCH.v"
`include "./../WRITEBACK/WRITEBACK.v"

module PROCESSOR( 
    input clock, 
    input reset,
    output zero
);

    wire [3:0] alu_control;
    wire regwrite;
    

    wire [31:0] FD_Inst_Code;
    wire [3:0] DE_Control;
    wire [31:0] in1;
    wire [31:0] in2;
    wire [4:0] rd;
    wire [31:0] EM_Result;
    wire [31:0] PC;
    wire [31:0] reg_omemory [10:0];


    FETCH FETCH_mod(clock,reset,FD_Inst_Code);
    
    DECODE DECODE_mod(clock,FD_Inst_Code,DE_control,in1,in2,rd);
    
    EXECUTE EXECUTE_mod(in1,in2,DE_control,EM_Result,zero);
    
    WRITEBACK WRITEBACK_mod(clock,reset,DE_regwrite,rd,EM_Result);
    

endmodule

PROCESSOR/PROCESSOR_tb.v
`include "PROCESSOR.v"

module stimulus ();
    
    reg clock;
    reg reset;
    wire zero;

    // Instantiating the processor!!!
    PROCESSOR test_processor(clock,reset,zero);

    initial begin
        $dumpfile("PROCESSOR_wave2.vcd");
        $dumpvars(0,stimulus);
    end

    initial begin
        reset = 1;
        #50 reset = 0;
    end

    initial begin
        clock = 0;
        forever #20 clock = ~clock;
    end

    initial
    #900 $finish;
    
endmodule

PROCESSOR/PROCESSOR_wave2.vcd
$date
	Wed Jun 14 16:51:02 2023
$end
$version
	Icarus Verilog
$end
$timescale
	1s
$end
$scope module stimulus $end
$var wire 1 ! zero $end
$var reg 1 " clock $end
$var reg 1 # reset $end
$scope module test_processor $end
$var wire 1 $ DE_regwrite $end
$var wire 32 % FD_Inst_Code [31:0] $end
$var wire 1 " clock $end
$var wire 1 # reset $end
$var wire 1 ! zero $end
$var wire 5 & rd [4:0] $end
$var wire 32 ' in2 [31:0] $end
$var wire 32 ( in1 [31:0] $end
$var wire 32 ) EM_Result [31:0] $end
$var wire 1 * DE_control $end
$scope module DECODE_mod $end
$var wire 32 + FD_Inst_Code [31:0] $end
$var wire 1 " clock $end
$var wire 1 , reset $end
$var wire 32 - in2 [31:0] $end
$var wire 32 . in1 [31:0] $end
$var reg 4 / DE_control [3:0] $end
$var reg 1 0 DE_regwrite $end
$var reg 3 1 funct3 [2:0] $end
$var reg 7 2 funct7 [6:0] $end
$var reg 7 3 opcode [6:0] $end
$var reg 5 4 rd [4:0] $end
$var reg 5 5 rs1 [4:0] $end
$var reg 5 6 rs2 [4:0] $end
$scope module reg_file_module $end
$var wire 1 " clock $end
$var wire 32 7 read_data1 [31:0] $end
$var wire 32 8 read_data2 [31:0] $end
$var wire 5 9 read_reg_num1 [4:0] $end
$var wire 5 : read_reg_num2 [4:0] $end
$var wire 1 , reset $end
$upscope $end
$upscope $end
$scope module EXECUTE_mod $end
$var wire 4 ; DE_control [3:0] $end
$var wire 32 < in1 [31:0] $end
$var wire 32 = in2 [31:0] $end
$var reg 32 > EM_Result [31:0] $end
$var reg 1 ! EM_zero_flag $end
$upscope $end
$scope module FETCH_mod $end
$var wire 32 ? FD_Inst_code [31:0] $end
$var wire 1 " clock $end
$var wire 1 # reset $end
$var wire 8 @ MD_Memory [7:0] $end
$var wire 1 A FD_Inst_Code $end
$var reg 32 B PC [31:0] $end
$scope module inst_mem $end
$var wire 32 C PC [31:0] $end
$var wire 1 " clock $end
$var wire 1 # reset $end
$var reg 8 D MD_Memory [7:0] $end
$upscope $end
$upscope $end
$scope module WRITEBACK_mod $end
$var wire 1 $ DE_regwrite $end
$var wire 32 E EM_Result [31:0] $end
$var wire 1 " clock $end
$var wire 5 F rd [4:0] $end
$var wire 1 # reset $end
$upscope $end
$upscope $end
$upscope $end
$enddefinitions $end
$comment Show the parameter values. $end
$dumpall
$end
#0
$dumpvars
bx F
bx E
bx D
b0 C
b0 B
xA
bx @
bz ?
bx >
bx =
bx <
b0x ;
bx :
bx 9
bx 8
bx 7
bx 6
bx 5
bx 4
bx 3
bx 2
bx 1
x0
bx /
bx .
bx -
z,
bz +
x*
bx )
bx (
bx '
bx &
bz %
z$
1#
0"
0!
$end
#20
1A
b110011 @
b110011 D
bz &
bz 4
bz F
bz 6
bz :
bz 5
bz 9
bz 3
bz 2
bz 1
1"
#40
0"
#50
0#
#60
b100 B
b100 C
1"
#80
0"
#100
xA
b1000 B
b1000 C
b10110011 @
b10110011 D
1"
#120
0"
#140
b1100 B
b1100 C
b110011 @
b110011 D
1"
#160
0"
#180
b10000 B
b10000 C
b10110011 @
b10110011 D
1"
#200
0"
#220
b10100 B
b10100 C
b110011 @
b110011 D
1"
#240
0"
#260
b11000 B
b11000 C
b10110011 @
b10110011 D
1"
#280
0"
#300
b11100 B
b11100 C
b110011 @
b110011 D
1"
#320
0"
#340
b100000 B
b100000 C
b10110011 @
b10110011 D
1"
#360
0"
#380
b100100 B
b100100 C
bx @
bx D
1"
#400
0"
#420
b101000 B
b101000 C
1"
#440
0"
#460
b101100 B
b101100 C
1"
#480
0"
#500
b110000 B
b110000 C
1"
#520
0"
#540
b110100 B
b110100 C
1"
#560
0"
#580
b111000 B
b111000 C
1"
#600
0"
#620
b111100 B
b111100 C
1"
#640
0"
#660
b1000000 B
b1000000 C
1"
#680
0"
#700
b1000100 B
b1000100 C
1"
#720
0"
#740
b1001000 B
b1001000 C
1"
#760
0"
#780
b1001100 B
b1001100 C
1"
#800
0"
#820
b1010000 B
b1010000 C
1"
#840
0"
#860
b1010100 B
b1010100 C
1"
#880
0"
#900
b1011000 B
b1011000 C
1"
